schubertpy/__init__.py
schubertpy/abstract_grassmannian.py
schubertpy/csv_bijection.py
schubertpy/grassmannian.py
schubertpy/isotropic_grassmannian.py
schubertpy/lc.py
schubertpy/mult_table.py
schubertpy/orthogonal_grassmannian.py
schubertpy/partition.py
schubertpy/qcalc.py
schubertpy/schur.py
schubertsage/__init__.py
schubertsage/conversion.py
schubertpy-1.0.5.dist-info/LICENSE
schubertpy-1.0.5.dist-info/METADATA
schubertpy-1.0.5.dist-info/WHEEL
schubertpy-1.0.5.dist-info/top_level.txt
schubertpy-1.0.5.dist-info/RECORD
