Metadata-Version: 2.2
Name: schubertpy
Version: 1.0.5
Summary: This Python module facilitates operations such as quantum Pieri rules, quantum Giambelli formulae, action and multiplication of Schubert classes, and conversion between different representations of Schubert classes
Home-page: https://github.com/tranduythanh/schubertpy
Author: Trần Duy Thanh
Author-email: fbtranduythanh@gmail.com
Requires-Python: >=3.6
License-File: LICENSE
Requires-Dist: gmpy2==2.2.1
Requires-Dist: mpmath==1.3.0
Requires-Dist: numpy==2.1.2
Requires-Dist: pandas==2.2.3
Requires-Dist: python-dateutil==2.9.0.post0
Requires-Dist: pytz==2024.2
Requires-Dist: six==1.16.0
Requires-Dist: sympy==1.13.3
Requires-Dist: tzdata==2024.2
Requires-Dist: matplotlib==3.9.2
Provides-Extra: passagemath
Requires-Dist: passagemath-combinat; extra == "passagemath"
Requires-Dist: passagemath-modules; extra == "passagemath"
Requires-Dist: passagemath-repl; extra == "passagemath"
Requires-Dist: passagemath-symbolics; extra == "passagemath"
Dynamic: author
Dynamic: author-email
Dynamic: description
Dynamic: description-content-type
Dynamic: home-page
Dynamic: provides-extra
Dynamic: requires-dist
Dynamic: requires-python
Dynamic: summary
